scholarmail/__init__.py
scholarmail/gen_html.py
scholarmail/get_email.py
scholarmail/scholarmail.py
scholarmail/temperate.html
scholarmail-1.1.0.dist-info/METADATA
scholarmail-1.1.0.dist-info/WHEEL
scholarmail-1.1.0.dist-info/entry_points.txt
scholarmail-1.1.0.dist-info/top_level.txt
scholarmail-1.1.0.dist-info/RECORD
