Metadata-Version: 2.1
Name: scholarmail
Version: 1.1.0
Summary: Please see github for more details.[https://github.com/hhhuang18/scholarmail]
Home-page: https://github.com/hhhuang18/myproject
Author: Hh Huang
Author-email: h976567853@gmail.com
License: MIT
Platform: UNKNOWN
Classifier: License :: OSI Approved :: MIT License
Classifier: Programming Language :: Python
Classifier: Programming Language :: Python :: 3
Classifier: Programming Language :: Python :: 3.6
Classifier: Programming Language :: Python :: Implementation :: CPython
Classifier: Programming Language :: Python :: Implementation :: PyPy
Requires-Python: >=3.6.0
Requires-Dist: pandas
Requires-Dist: Jinja2
Requires-Dist: python-socks
Requires-Dist: lxml
Requires-Dist: tqdm
Requires-Dist: goslate
